MANIFEST.in
README.rst
VERSION
setup.py
grano_client.egg-info/PKG-INFO
grano_client.egg-info/SOURCES.txt
grano_client.egg-info/dependency_links.txt
grano_client.egg-info/entry_points.txt
grano_client.egg-info/not-zip-safe
grano_client.egg-info/requires.txt
grano_client.egg-info/top_level.txt
granoclient/__init__.py
granoclient/base.py
granoclient/common.py
granoclient/entity.py
granoclient/loader.py
granoclient/project.py
granoclient/relation.py
granoclient/schema.py