Metadata-Version: 1.0
Name: grano-client
Version: 0.4.7
Summary: Client library for grano, a social network analysis tool.
Home-page: https://github.com/ANCIR/grano-client
Author: Code for Africa / ANCIR
Author-email: support@codeforafrica.org
License: MIT
Keywords: data client rest grano sna ddj journalism
Platform: UNKNOWN
